{
    "reusePaths": {},
    "CompUnits": {
        "lvc_i2c_pkg_d": {
            "out": "lvc_i2c_pkg_d.o",
            "mod": "lvc_i2c_pkg",
            "bytes": 4670738,
            "text": 2064699,
            "cls": 2049619,
            "mode": 4,
            "checksum": 4294967295,
            "archive": "archive.0/__vcs_msglog_UF52e_1_archive_1.a"
        },
        "_vcs_msglog_d": {
            "out": "_vcs_msglog_d.o",
            "mod": "_vcs_msglog",
            "bytes": 45780,
            "text": 735,
            "mode": 4,
            "checksum": 4294967295,
            "archive": "archive.0/__vcs_msglog_UF52e_1_archive_1.a"
        }
    },
    "Modules": {
        "...MASTER...": {
            "start_perf": [
                9.8483841419219971,
                9.1899719999999991,
                0.50982899999999998,
                405904,
                431024,
                1672925014.6745501,
                57602102350442
            ],
            "child_modules": {
                "vcs_paramclassrepository_UF52ed": 1,
                "rkv_i2c_pkg": 1,
                "uvm_pkg": 1,
                "lvc_i2c_pkg": 1,
                "pc__vcs_msglog": 1,
                "lvc_apb_pkg": 1,
                "std": 1,
                "_vcs_msglog": 1
            },
            "end_perf": [
                9.8490841388702393,
                9.1906350000000003,
                0.50986500000000001,
                405904,
                431024,
                57602104286168,
                0,
                0
            ],
            "nMops": 0,
            "nQuads": 0,
            "nRouts": 5
        },
        "lvc_i2c_pkg": {
            "svclass": [
                "lvc_configuration",
                12097,
                964,
                10,
                10,
                2708757170585696712,
                "lvc_i2c_configuration",
                670734,
                68003,
                20,
                19,
                1943104463212659733,
                "lvc_i2c_agent_configuration",
                77273,
                7417,
                13,
                13,
                -1851766196339962603,
                "lvc_i2c_transaction",
                323733,
                32760,
                13,
                12,
                -7274046663751038896,
                "lvc_i2c_bfm_common",
                20974,
                2725,
                30,
                16,
                8711039859241879408,
                "lvc_i2c_master_transaction",
                42986,
                3957,
                12,
                11,
                -2379331327186413632,
                "lvc_i2c_master_monitor_common",
                81560,
                11127,
                152,
                15,
                -9095523992493303917,
                "lvc_i2c_master_monitor",
                38603,
                3627,
                46,
                15,
                -3876254155499913783,
                "lvc_i2c_master_monitor::lvc_i2c_master_cov_trans",
                0,
                0,
                0,
                0,
                0,
                "lvc_i2c_master_driver_callback",
                8249,
                554,
                11,
                11,
                843707476457601664,
                "lvc_i2c_master_driver_common",
                261783,
                28606,
                881,
                27,
                -1621738086199275651,
                "lvc_i2c_master_agent",
                45555,
                4284,
                19,
                14,
                -1032320271025885963,
                "lvc_i2c_slave_transaction",
                30609,
                2922,
                12,
                11,
                -4426760780633006683,
                "lvc_i2c_slave_monitor_common",
                81332,
                11091,
                152,
                15,
                6750403892549153797,
                "lvc_i2c_slave_monitor",
                39095,
                3647,
                48,
                15,
                -5991289036018709291,
                "lvc_i2c_slave_monitor::lvc_i2c_slave_cov_trans",
                0,
                0,
                0,
                0,
                0,
                "lvc_i2c_slave_driver_common",
                105569,
                13713,
                282,
                16,
                -357358078767413515,
                "lvc_i2c_slave_agent",
                46636,
                4433,
                19,
                14,
                7415185838954543879,
                "lvc_i2c_system_configuration",
                119971,
                12331,
                23,
                22,
                -8799919357542244782,
                "lvc_i2c_system_env",
                42860,
                4298,
                30,
                18,
                -5942760264536073654
            ],
            "start_perf": [
                9.8602499961853027,
                9.1906350000000003,
                0.52103100000000002,
                405904,
                431024,
                1672925014.6864159,
                57602135648755
            ],
            "child_modules": {},
            "significant_routs": [
                [
                    1572,
                    "F_VCSClass_lvc_i2c_pkglvc_i2c_configuration_lvc_i2c_configuration3a3a__m_uvm_field_automation",
                    4304214978,
                    522828,
                    52736
                ],
                [
                    1576,
                    "F_VCSClass_lvc_i2c_pkglvc_i2c_configuration_lvc_i2c_configuration3a3ais_valid",
                    502100040,
                    97140,
                    8137
                ],
                [
                    1589,
                    "F_VCSClass_lvc_i2c_pkglvc_i2c_agent_configuration_lvc_i2c_agent_configuration3a3a__m_uvm_field_automation",
                    292610787,
                    57268,
                    5637
                ],
                [
                    1599,
                    "F_VCSClass_lvc_i2c_pkglvc_i2c_transaction_lvc_i2c_transaction3a3a__m_uvm_field_automation",
                    2020766600,
                    284095,
                    29330
                ],
                [
                    1620,
                    "F_VCSClass_lvc_i2c_pkglvc_i2c_master_transaction_lvc_i2c_master_transaction3a3ais_valid",
                    140887618,
                    31806,
                    2648
                ],
                [
                    1665,
                    "F_VCSClass_lvc_i2c_pkglvc_i2c_master_agent_lvc_i2c_master_agent3a3a__m_uvm_field_automation",
                    220250863,
                    19593,
                    1996
                ],
                [
                    1667,
                    "F_VCSClass_lvc_i2c_pkglvc_i2c_master_agent_lvc_i2c_master_agent3a3abuild_phase",
                    141775965,
                    13608,
                    1399
                ],
                [
                    1677,
                    "F_VCSClass_lvc_i2c_pkglvc_i2c_slave_transaction_lvc_i2c_slave_transaction3a3ais_valid",
                    205989261,
                    20499,
                    1848
                ],
                [
                    1691,
                    "F_VCSClass_lvc_i2c_pkglvc_i2c_slave_monitor_lvc_i2c_slave_monitor3a3a__m_uvm_field_automation",
                    137799227,
                    13292,
                    1396
                ],
                [
                    1713,
                    "F_VCSClass_lvc_i2c_pkglvc_i2c_slave_agent_lvc_i2c_slave_agent3a3a__m_uvm_field_automation",
                    209805497,
                    19593,
                    1996
                ],
                [
                    1715,
                    "F_VCSClass_lvc_i2c_pkglvc_i2c_slave_agent_lvc_i2c_slave_agent3a3abuild_phase",
                    144113351,
                    14689,
                    1548
                ],
                [
                    1735,
                    "F_VCSClass_lvc_i2c_pkglvc_i2c_system_configuration_lvc_i2c_system_configuration3a3a__m_uvm_field_automation",
                    717181794,
                    98366,
                    10090
                ]
            ],
            "end_perf": [
                14.736082077026367,
                13.742255,
                0.69555500000000003,
                408764,
                431024,
                57615756353443,
                2875367100509148050,
                0
            ],
            "nMops": 217881,
            "nQuads": 64903,
            "nRouts": 1867
        },
        "_vcs_msglog": {
            "svclass": [
                "rkv_i2c_if_1146083354_12_vcs_virt_intf_C",
                0,
                0,
                0,
                0,
                0,
                "lvc_i2c_if_1146083354_12_vcs_virt_intf_C",
                0,
                0,
                0,
                0,
                0,
                "lvc_apb_if_1146083354_12_vcs_virt_intf_C",
                0,
                0,
                0,
                0,
                0
            ],
            "start_perf": [
                14.736356973648071,
                13.742516999999999,
                0.69556899999999999,
                408764,
                431024,
                1672925019.5625229,
                57615757196301
            ],
            "child_modules": {},
            "end_perf": [
                14.743941068649292,
                13.747883,
                0.69759599999999999,
                408764,
                431024,
                57615778289040,
                6505974944744156591,
                0
            ],
            "nMops": 80,
            "nQuads": 30,
            "nRouts": 10
        }
    },
    "ObjArchives": [
        {
            "archive": "archive.0/__vcs_msglog_UF52e_1_archive_1.a",
            "size": 4836458,
            "objects": [
                [
                    "lvc_i2c_pkg_d.o",
                    4670738
                ],
                [
                    "_vcs_msglog_d.o",
                    45780
                ],
                [
                    "SIMB.o",
                    119940
                ]
            ]
        }
    ],
    "stat": {
        "ru_self_end": {
            "ru_nivcsw": 107,
            "ru_utime_sec": 13.865174,
            "ru_stime_sec": 0.75905999999999996,
            "ru_maxrss_kb": 236724,
            "ru_minflt": 125923,
            "ru_nvcsw": 1435,
            "ru_majflt": 22
        },
        "ru_childs_end": {
            "ru_nivcsw": 287,
            "ru_utime_sec": 17.385311000000002,
            "ru_stime_sec": 0.99889799999999995,
            "ru_maxrss_kb": 195212,
            "ru_minflt": 73690,
            "ru_nvcsw": 121,
            "ru_majflt": 19
        },
        "cpu_cycles_end": 57630900468240,
        "peak_mem_kb": 431024
    }
}